odoo/addons/product_supplierinfo_for_customer_invoice/README.rst
odoo/addons/product_supplierinfo_for_customer_invoice/__init__.py
odoo/addons/product_supplierinfo_for_customer_invoice/__manifest__.py
odoo/addons/product_supplierinfo_for_customer_invoice/i18n/de.po
odoo/addons/product_supplierinfo_for_customer_invoice/i18n/es.po
odoo/addons/product_supplierinfo_for_customer_invoice/i18n/it.po
odoo/addons/product_supplierinfo_for_customer_invoice/i18n/product_supplierinfo_for_customer_invoice.pot
odoo/addons/product_supplierinfo_for_customer_invoice/i18n/pt.po
odoo/addons/product_supplierinfo_for_customer_invoice/i18n/pt_BR.po
odoo/addons/product_supplierinfo_for_customer_invoice/models/__init__.py
odoo/addons/product_supplierinfo_for_customer_invoice/models/account_move_line.py
odoo/addons/product_supplierinfo_for_customer_invoice/readme/CONTRIBUTORS.rst
odoo/addons/product_supplierinfo_for_customer_invoice/readme/DESCRIPTION.rst
odoo/addons/product_supplierinfo_for_customer_invoice/static/description/icon.png
odoo/addons/product_supplierinfo_for_customer_invoice/static/description/index.html
odoo/addons/product_supplierinfo_for_customer_invoice/tests/__init__.py
odoo/addons/product_supplierinfo_for_customer_invoice/tests/test_product_supplierinfo_for_customer_invoice.py
odoo/addons/product_supplierinfo_for_customer_invoice/views/account_move_view.xml
odoo13_addon_product_supplierinfo_for_customer_invoice-13.0.1.0.1.dev7.dist-info/METADATA
odoo13_addon_product_supplierinfo_for_customer_invoice-13.0.1.0.1.dev7.dist-info/WHEEL
odoo13_addon_product_supplierinfo_for_customer_invoice-13.0.1.0.1.dev7.dist-info/top_level.txt
odoo13_addon_product_supplierinfo_for_customer_invoice-13.0.1.0.1.dev7.dist-info/RECORD
